HubNLP/__init__.py
HubNLP/attention.py
HubNLP/core.py
HubNLP-0.3.dist-info/LICENSE
HubNLP-0.3.dist-info/METADATA
HubNLP-0.3.dist-info/WHEEL
HubNLP-0.3.dist-info/top_level.txt
HubNLP-0.3.dist-info/RECORD
